gravityyaml/__init__.py
gravityyaml/__main__.py
gravityyaml/cli.py
gravityyaml/database.py
gravityyaml/database.sql
gravityyaml/errors.py
gravityyaml/gravityyaml.py
gravityyaml-0.1.0.dist-info/LICENSES/CC-BY-4.0.txt
gravityyaml-0.1.0.dist-info/LICENSES/CC-BY-SA-4.0.txt
gravityyaml-0.1.0.dist-info/LICENSES/CC0-1.0.txt
gravityyaml-0.1.0.dist-info/LICENSES/EUPL-1.2.txt
gravityyaml-0.1.0.dist-info/LICENSES/LicenseRef-DCO.txt
gravityyaml-0.1.0.dist-info/LICENSES/MIT.txt
gravityyaml-0.1.0.dist-info/METADATA
gravityyaml-0.1.0.dist-info/WHEEL
gravityyaml-0.1.0.dist-info/entry_points.txt
gravityyaml-0.1.0.dist-info/RECORD
