Metadata-Version: 2.1
Name: gravityyaml
Version: 0.1.0
Summary: Store your Pi-hole gravity.db configs in a single YAML file
License: MIT
Author: Sidings Media
Requires-Python: >=3.11,<4.0
Classifier: License :: OSI Approved :: MIT License
Classifier: Programming Language :: Python :: 3
Classifier: Programming Language :: Python :: 3.11
Requires-Dist: PyYAML (>=6.0.1,<7.0.0)
